nonprobest.py
nonprobest-1.0.dist-info/LICENSE
nonprobest-1.0.dist-info/WHEEL
nonprobest-1.0.dist-info/METADATA
nonprobest-1.0.dist-info/RECORD
