Metadata-Version: 2.1
Name: nonprobest
Version: 1.0
Summary: Python package for statistical inference from non-probability samples
Author-email: Luis Castro Martín <luiscastro193@gmail.com>
Classifier: License :: OSI Approved :: GNU General Public License v3 or later (GPLv3+)
Requires-Dist: numpy
Requires-Dist: pandas
Requires-Dist: scipy
Requires-Dist: scikit-learn>=1.1
Project-URL: Home, https://github.com/luiscastro193/nonprobest
